{
  "gitSyncId": "686bbf135dd1861a2c0bf90b_a8d06b26-3f45-499a-a83c-923680e1ec12",
  "unpublishedPage": {
    "isHidden": false,
    "layouts": [
      {
        "dsl": {
          "backgroundColor": "none",
          "bottomRow": 980,
          "canExtend": true,
          "containerStyle": "none",
          "detachFromLayout": true,
          "dynamicBindingPathList": [],
          "dynamicTriggerPathList": [],
          "leftColumn": 0,
          "minHeight": 1292,
          "parentColumnSpace": 1,
          "parentRowSpace": 1,
          "rightColumn": 4896,
          "snapColumns": 64,
          "snapRows": 124,
          "topRow": 0,
          "type": "CANVAS_WIDGET",
          "version": 94,
          "widgetId": "0",
          "widgetName": "MainContainer"
        }
      }
    ],
    "name": "Daikin Delivery Schedule",
    "slug": "daikin-delivery-schedule"
  }
}